FishTaco-1.1.6.data/scripts/run_fishtaco.py
FishTaco-1.1.6.data/scripts/test_fishtaco.py
fishtaco/__init__.py
fishtaco/compute_contribution_to_DA.py
fishtaco/compute_differential_abundance.py
fishtaco/compute_pathway_abundance.py
fishtaco/compute_shapley_value_from_subsets.py
fishtaco/learn_non_neg_elastic_net_with_prior.py
fishtaco/data/KOvsMODULE_BACTERIAL_KEGG_2013_07_15.tab
fishtaco/data/KOvsPATHWAY_BACTERIAL_KEGG_2013_07_15.tab
fishtaco/examples/KO_vs_SAMPLE_MUSiCC.tab
fishtaco/examples/METAPHLAN_taxa_vs_KO_only_K00001.tab
fishtaco/examples/METAPHLAN_taxa_vs_KO_only_K00001_K00054.tab
fishtaco/examples/METAPHLAN_taxa_vs_SAMPLE_for_K00001.tab
fishtaco/examples/PATHWAY_vs_SAMPLE_MUSiCC.tab
fishtaco/examples/SAMPLE_vs_CLASS.tab
fishtaco/examples/WGS_KO_vs_SAMPLE_MUSiCC_only_K00001.tab
fishtaco/examples/WGS_KO_vs_SAMPLE_MUSiCC_only_K00001_K00054.tab
fishtaco/examples/output/fishtaco_out_FDR_correction_STAT_taxa_contributions_SCORE_wilcoxon_ASSESSMENT_single_taxa.tab
fishtaco/examples/output/fishtaco_out_de_novo_inf_STAT_DA_function_SCORE_wilcoxon_ASSESSMENT_permuted_shapley_orderings.tab
fishtaco/examples/output/fishtaco_out_de_novo_inf_STAT_DA_function_SCORE_wilcoxon_ASSESSMENT_single_taxa.tab
fishtaco/examples/output/fishtaco_out_de_novo_inf_STAT_DA_taxa_SCORE_wilcoxon_ASSESSMENT_permuted_shapley_orderings.tab
fishtaco/examples/output/fishtaco_out_de_novo_inf_STAT_DA_taxa_SCORE_wilcoxon_ASSESSMENT_single_taxa.tab
fishtaco/examples/output/fishtaco_out_de_novo_inf_STAT_mean_stat_SCORE_wilcoxon_ASSESSMENT_permuted_shapley_orderings.tab
fishtaco/examples/output/fishtaco_out_de_novo_inf_STAT_mean_stat_SCORE_wilcoxon_ASSESSMENT_single_taxa.tab
fishtaco/examples/output/fishtaco_out_de_novo_inf_STAT_median_stat_SCORE_wilcoxon_ASSESSMENT_permuted_shapley_orderings.tab
fishtaco/examples/output/fishtaco_out_de_novo_inf_STAT_median_stat_SCORE_wilcoxon_ASSESSMENT_single_taxa.tab
FishTaco-1.1.6.dist-info/AUTHORS.rst
FishTaco-1.1.6.dist-info/LICENSE
FishTaco-1.1.6.dist-info/METADATA
FishTaco-1.1.6.dist-info/WHEEL
FishTaco-1.1.6.dist-info/top_level.txt
FishTaco-1.1.6.dist-info/RECORD
