Metadata-Version: 2.1
Name: FishTaco
Version: 1.1.6
Summary: FishTaco: a metagenomic computational framework, aiming to identify the taxa that are driving functional shifts in microbiomes.
Home-page: http://omanor.github.io/fishtaco/
Author: Ohad Manor
Author-email: omanor@gmail.com
License: UNKNOWN
Platform: UNKNOWN
Classifier: License :: Free for non-commercial use
License-File: LICENSE
License-File: AUTHORS.rst
Requires-Dist: NumPy (>=1.17.0)
Requires-Dist: SciPy (>=1.3.0)
Requires-Dist: scikit-learn (>=0.21.3)
Requires-Dist: statsmodels (>=0.10.1)
Requires-Dist: pandas (>=0.25.0)
Requires-Dist: MUSiCC (>=1.0.3)
